src/__init__.py
src/blast.py
src/gui/__init__.py
src/gui/blast_panel.py
src/gui/loading_blast_panel.py
src/gui/main_panel.py
src/gui/mapping_panel.py
src/gui/prepare_panel.py
src/gui/prepare_window.py
src/gui/primer_panel.py
src/gui/splitter_window.py
src/gui_start.py
src/logic/Blast.py
src/logic/GenomeDownloader.py
src/logic/GenomeMapping.py
src/logic/PrimersMaking.py
src/logic/Splitter.py
src/logic/__init__.py
src/mapping.py
src/prepare.py
src/primer_3.py
src/run_gui.py
src/splitter.py
s3finder-0.1.7.dist-info/entry_points.txt
s3finder-0.1.7.dist-info/WHEEL
s3finder-0.1.7.dist-info/METADATA
s3finder-0.1.7.dist-info/RECORD
